{"isAddBias":true,"inputs":[{"id":0,"x":0.1,"incoming":[]},{"id":1,"x":0.1,"incoming":[]},{"id":2,"x":0.1,"incoming":[]},{"id":3,"x":0.1,"incoming":[]},{"id":4,"x":0.1,"incoming":[]},{"id":5,"x":0.1,"incoming":[]},{"id":6,"x":0.1,"incoming":[]}],"hidden":[],"outputs":[{"id":7,"x":0.9,"incoming":[{"fromId":0,"weight":2.287622,"enabled":true},{"fromId":1,"weight":0.25196072,"enabled":true},{"fromId":2,"weight":1.3192992,"enabled":true},{"fromId":3,"weight":-1.7426059,"enabled":true},{"fromId":4,"weight":-1.5634545,"enabled":true},{"fromId":5,"weight":0.52925855,"enabled":true},{"fromId":6,"weight":0.75111914,"enabled":true}]},{"id":8,"x":0.9,"incoming":[{"fromId":0,"weight":-0.049533464,"enabled":true},{"fromId":1,"weight":0.41866946,"enabled":true},{"fromId":2,"weight":-0.2330631,"enabled":true},{"fromId":3,"weight":-0.2034651,"enabled":true},{"fromId":4,"weight":2.0579987,"enabled":true},{"fromId":5,"weight":0.42670634,"enabled":true},{"fromId":6,"weight":-0.14521381,"enabled":true}]},{"id":9,"x":0.9,"incoming":[{"fromId":0,"weight":-2.005923,"enabled":true},{"fromId":1,"weight":-0.72926104,"enabled":true},{"fromId":2,"weight":-1.7773548,"enabled":true},{"fromId":3,"weight":0.1276759,"enabled":true},{"fromId":4,"weight":0.4192823,"enabled":true},{"fromId":5,"weight":0.3063931,"enabled":true},{"fromId":6,"weight":1.551717,"enabled":true}]},{"id":10,"x":0.9,"incoming":[{"fromId":0,"weight":0.74717176,"enabled":true},{"fromId":1,"weight":-0.15001294,"enabled":true},{"fromId":2,"weight":-1.0036668,"enabled":true},{"fromId":3,"weight":0.19483545,"enabled":true},{"fromId":4,"weight":-0.30642778,"enabled":true},{"fromId":5,"weight":-0.36273694,"enabled":true},{"fromId":6,"weight":-1.2537394,"enabled":true}]}]}