{"isAddBias":true,"inputs":[{"id":0,"x":0.1,"incoming":[]},{"id":1,"x":0.1,"incoming":[]},{"id":2,"x":0.1,"incoming":[]},{"id":3,"x":0.1,"incoming":[]},{"id":4,"x":0.1,"incoming":[]},{"id":5,"x":0.1,"incoming":[]},{"id":6,"x":0.1,"incoming":[]},{"id":7,"x":0.1,"incoming":[]},{"id":8,"x":0.1,"incoming":[]},{"id":9,"x":0.1,"incoming":[]},{"id":10,"x":0.1,"incoming":[]},{"id":11,"x":0.1,"incoming":[]}],"hidden":[],"outputs":[{"id":12,"x":0.9,"incoming":[{"fromId":0,"weight":-0.7370601,"enabled":true},{"fromId":1,"weight":-0.75585836,"enabled":true},{"fromId":2,"weight":-0.17319728,"enabled":true},{"fromId":3,"weight":-1.3345883,"enabled":true},{"fromId":4,"weight":0.71821624,"enabled":true},{"fromId":5,"weight":0.07947642,"enabled":true},{"fromId":6,"weight":1.2083672,"enabled":true},{"fromId":7,"weight":3.100381,"enabled":true},{"fromId":8,"weight":1.152842,"enabled":true},{"fromId":9,"weight":0.6437803,"enabled":true},{"fromId":10,"weight":1.6998248,"enabled":true},{"fromId":11,"weight":0.6146297,"enabled":true}]},{"id":13,"x":0.9,"incoming":[{"fromId":0,"weight":-0.82603115,"enabled":true},{"fromId":1,"weight":-0.84422356,"enabled":true},{"fromId":2,"weight":0.44126692,"enabled":true},{"fromId":3,"weight":-0.22318745,"enabled":true},{"fromId":4,"weight":0.32774028,"enabled":true},{"fromId":5,"weight":1.2858477,"enabled":true},{"fromId":6,"weight":-0.15803221,"enabled":true},{"fromId":7,"weight":-1.1943815,"enabled":true},{"fromId":8,"weight":0.20969217,"enabled":true},{"fromId":9,"weight":2.0569339,"enabled":true},{"fromId":10,"weight":1.5565816,"enabled":true},{"fromId":11,"weight":0.35891867,"enabled":true}]},{"id":14,"x":0.9,"incoming":[{"fromId":0,"weight":0.4250533,"enabled":true},{"fromId":1,"weight":-0.76673067,"enabled":true},{"fromId":2,"weight":-0.87840337,"enabled":true},{"fromId":3,"weight":2.1732965,"enabled":true},{"fromId":4,"weight":-0.9806507,"enabled":true},{"fromId":5,"weight":-0.27784768,"enabled":true},{"fromId":6,"weight":-1.3130362,"enabled":true},{"fromId":7,"weight":1.0442648,"enabled":true},{"fromId":8,"weight":1.262929,"enabled":true},{"fromId":9,"weight":-0.13810003,"enabled":true},{"fromId":10,"weight":0.57692343,"enabled":true},{"fromId":11,"weight":-0.6799289,"enabled":true}]},{"id":15,"x":0.9,"incoming":[{"fromId":0,"weight":-1.1162121,"enabled":true},{"fromId":1,"weight":1.2052324,"enabled":true},{"fromId":2,"weight":-0.4535099,"enabled":true},{"fromId":3,"weight":-0.11941186,"enabled":true},{"fromId":4,"weight":-0.5592455,"enabled":true},{"fromId":5,"weight":-0.33309433,"enabled":true},{"fromId":6,"weight":0.3144621,"enabled":true},{"fromId":7,"weight":0.56784105,"enabled":true},{"fromId":8,"weight":-1.1446613,"enabled":true},{"fromId":9,"weight":1.3130739,"enabled":true},{"fromId":10,"weight":-1.6241028,"enabled":true},{"fromId":11,"weight":0.11313485,"enabled":true}]}]}