{"isAddBias":true,"inputs":[{"id":0,"x":0.1,"incoming":[]},{"id":1,"x":0.1,"incoming":[]},{"id":2,"x":0.1,"incoming":[]},{"id":3,"x":0.1,"incoming":[]},{"id":4,"x":0.1,"incoming":[]},{"id":5,"x":0.1,"incoming":[]},{"id":6,"x":0.1,"incoming":[]}],"hidden":[{"id":27,"x":0.49999997,"incoming":[{"fromId":5,"weight":0.64610565,"enabled":true},{"fromId":0,"weight":0.034476433,"enabled":true}]}],"outputs":[{"id":7,"x":0.9,"incoming":[{"fromId":0,"weight":0.69843704,"enabled":true},{"fromId":1,"weight":1.9738327,"enabled":true},{"fromId":2,"weight":1.8222997,"enabled":true},{"fromId":3,"weight":-2.3070486,"enabled":true},{"fromId":4,"weight":-1.0525712,"enabled":true},{"fromId":5,"weight":-0.37364262,"enabled":false},{"fromId":6,"weight":0.21494958,"enabled":true},{"fromId":27,"weight":-0.11991392,"enabled":true}]},{"id":8,"x":0.9,"incoming":[{"fromId":0,"weight":0.21788113,"enabled":true},{"fromId":1,"weight":-0.30427694,"enabled":true},{"fromId":2,"weight":-0.11284371,"enabled":true},{"fromId":3,"weight":-0.2748471,"enabled":true},{"fromId":4,"weight":0.34443417,"enabled":true},{"fromId":5,"weight":0.23177098,"enabled":true},{"fromId":6,"weight":-1.2494651,"enabled":true}]},{"id":9,"x":0.9,"incoming":[{"fromId":0,"weight":0.8454945,"enabled":true},{"fromId":1,"weight":-0.03652461,"enabled":true},{"fromId":2,"weight":0.47535446,"enabled":true},{"fromId":3,"weight":-1.6173711,"enabled":true},{"fromId":4,"weight":-1.061387,"enabled":true},{"fromId":5,"weight":0.4753396,"enabled":true},{"fromId":6,"weight":-1.595007,"enabled":true}]},{"id":10,"x":0.9,"incoming":[{"fromId":0,"weight":0.5112275,"enabled":true},{"fromId":1,"weight":-0.081103854,"enabled":true},{"fromId":2,"weight":-1.1520714,"enabled":true},{"fromId":3,"weight":-1.0274156,"enabled":true},{"fromId":4,"weight":-0.60688806,"enabled":true},{"fromId":5,"weight":-0.2449026,"enabled":true},{"fromId":6,"weight":0.7179036,"enabled":true}]}]}