{"isAddBias":true,"inputs":[{"id":0,"x":0.1,"incoming":[]},{"id":1,"x":0.1,"incoming":[]},{"id":2,"x":0.1,"incoming":[]},{"id":3,"x":0.1,"incoming":[]},{"id":4,"x":0.1,"incoming":[]},{"id":5,"x":0.1,"incoming":[]},{"id":6,"x":0.1,"incoming":[]}],"hidden":[],"outputs":[{"id":7,"x":0.9,"incoming":[{"fromId":0,"weight":0.65856254,"enabled":true},{"fromId":1,"weight":-1.5226173,"enabled":true},{"fromId":2,"weight":0.082121514,"enabled":true},{"fromId":3,"weight":-0.15923262,"enabled":true},{"fromId":4,"weight":0.68818825,"enabled":true},{"fromId":5,"weight":-1.9634509,"enabled":true},{"fromId":6,"weight":0.805156,"enabled":true}]},{"id":8,"x":0.9,"incoming":[{"fromId":0,"weight":-0.79386353,"enabled":true},{"fromId":1,"weight":-0.9103223,"enabled":true},{"fromId":2,"weight":1.7875082,"enabled":true},{"fromId":3,"weight":1.0058794,"enabled":true},{"fromId":4,"weight":-1.3623943,"enabled":true},{"fromId":5,"weight":0.1089561,"enabled":true},{"fromId":6,"weight":0.61495566,"enabled":true}]},{"id":9,"x":0.9,"incoming":[{"fromId":0,"weight":0.14835672,"enabled":true},{"fromId":1,"weight":-0.6335549,"enabled":true},{"fromId":2,"weight":-1.2506117,"enabled":true},{"fromId":3,"weight":-2.2472148,"enabled":true},{"fromId":4,"weight":-1.1253915,"enabled":true},{"fromId":5,"weight":0.73015213,"enabled":true},{"fromId":6,"weight":-1.4986774,"enabled":true}]},{"id":10,"x":0.9,"incoming":[{"fromId":0,"weight":-1.470507,"enabled":true},{"fromId":1,"weight":-0.37462363,"enabled":true},{"fromId":2,"weight":0.21044265,"enabled":true},{"fromId":3,"weight":-0.43199766,"enabled":true},{"fromId":4,"weight":-0.27944905,"enabled":true},{"fromId":5,"weight":1.6117079,"enabled":true},{"fromId":6,"weight":0.91325814,"enabled":true}]}]}