{"isAddBias":true,"inputs":[{"id":0,"x":0.1,"incoming":[]},{"id":1,"x":0.1,"incoming":[]},{"id":2,"x":0.1,"incoming":[]},{"id":3,"x":0.1,"incoming":[]},{"id":4,"x":0.1,"incoming":[]},{"id":5,"x":0.1,"incoming":[]},{"id":6,"x":0.1,"incoming":[]}],"hidden":[],"outputs":[{"id":7,"x":0.9,"incoming":[{"fromId":0,"weight":0.9418027,"enabled":true},{"fromId":1,"weight":1.6922036,"enabled":true},{"fromId":2,"weight":-0.4098605,"enabled":true},{"fromId":3,"weight":-0.45416918,"enabled":true},{"fromId":4,"weight":-0.60319865,"enabled":true},{"fromId":5,"weight":0.6422355,"enabled":true},{"fromId":6,"weight":0.4961258,"enabled":true}]},{"id":8,"x":0.9,"incoming":[{"fromId":0,"weight":-1.3506112,"enabled":true},{"fromId":1,"weight":-1.6596286,"enabled":true},{"fromId":2,"weight":-0.34674937,"enabled":true},{"fromId":3,"weight":0.58053964,"enabled":true},{"fromId":4,"weight":-2.1367614,"enabled":true},{"fromId":5,"weight":-0.84931636,"enabled":true},{"fromId":6,"weight":-0.4868658,"enabled":true}]},{"id":9,"x":0.9,"incoming":[{"fromId":0,"weight":-0.31767538,"enabled":true},{"fromId":1,"weight":-0.7671077,"enabled":true},{"fromId":2,"weight":0.986875,"enabled":true},{"fromId":3,"weight":2.1984525,"enabled":true},{"fromId":4,"weight":-2.3534064,"enabled":true},{"fromId":5,"weight":1.5716808,"enabled":true},{"fromId":6,"weight":0.77665955,"enabled":true}]},{"id":10,"x":0.9,"incoming":[{"fromId":0,"weight":-0.591817,"enabled":true},{"fromId":1,"weight":-1.9737699,"enabled":true},{"fromId":2,"weight":-2.5269713,"enabled":true},{"fromId":3,"weight":0.015067369,"enabled":true},{"fromId":4,"weight":0.3964844,"enabled":true},{"fromId":5,"weight":0.11154206,"enabled":true},{"fromId":6,"weight":-0.3734688,"enabled":true}]}]}