{"isAddBias":true,"inputs":[{"id":0,"x":0.1,"incoming":[]},{"id":1,"x":0.1,"incoming":[]},{"id":2,"x":0.1,"incoming":[]},{"id":3,"x":0.1,"incoming":[]},{"id":4,"x":0.1,"incoming":[]},{"id":5,"x":0.1,"incoming":[]},{"id":6,"x":0.1,"incoming":[]},{"id":7,"x":0.1,"incoming":[]}],"hidden":[],"outputs":[{"id":8,"x":0.9,"incoming":[{"fromId":0,"weight":0.8674258,"enabled":true},{"fromId":1,"weight":-0.50451875,"enabled":true},{"fromId":2,"weight":-0.26329902,"enabled":true},{"fromId":3,"weight":1.0308632,"enabled":true},{"fromId":4,"weight":1.8786577,"enabled":true},{"fromId":5,"weight":1.4538445,"enabled":true},{"fromId":6,"weight":0.114427,"enabled":true},{"fromId":7,"weight":0.1845071,"enabled":true}]},{"id":9,"x":0.9,"incoming":[{"fromId":0,"weight":0.09616675,"enabled":true},{"fromId":1,"weight":2.1238787,"enabled":true},{"fromId":2,"weight":1.3610569,"enabled":true},{"fromId":3,"weight":-0.48358256,"enabled":true},{"fromId":4,"weight":0.9609014,"enabled":true},{"fromId":5,"weight":-0.5912983,"enabled":true},{"fromId":6,"weight":2.4611785,"enabled":true},{"fromId":7,"weight":0.122460485,"enabled":true}]},{"id":10,"x":0.9,"incoming":[{"fromId":0,"weight":-0.32406464,"enabled":true},{"fromId":1,"weight":1.7863446,"enabled":true},{"fromId":2,"weight":0.5255975,"enabled":true},{"fromId":3,"weight":0.71705884,"enabled":true},{"fromId":4,"weight":2.184301,"enabled":true},{"fromId":5,"weight":2.2415628,"enabled":true},{"fromId":6,"weight":0.066174805,"enabled":true},{"fromId":7,"weight":-1.587837,"enabled":true}]},{"id":11,"x":0.9,"incoming":[{"fromId":0,"weight":-0.67358434,"enabled":true},{"fromId":1,"weight":1.4087512,"enabled":true},{"fromId":2,"weight":-0.040632606,"enabled":true},{"fromId":3,"weight":-2.3691137,"enabled":true},{"fromId":4,"weight":-0.103291884,"enabled":true},{"fromId":5,"weight":-1.9744093,"enabled":true},{"fromId":6,"weight":-0.2746621,"enabled":true},{"fromId":7,"weight":0.7563059,"enabled":true}]}]}